jupyterlab_nbgallery/__init__.py
jupyterlab_nbgallery/_version.py
jupyterlab_nbgallery/handlers.py
jupyterlab_nbgallery-3.0.6.data/data/etc/jupyter/jupyter_server_config.d/jupyterlab_nbgallery.json
jupyterlab_nbgallery-3.0.6.data/data/share/jupyter/labextensions/@jupyterlab-nbgallery/autodownload/package.json
jupyterlab_nbgallery-3.0.6.data/data/share/jupyter/labextensions/@jupyterlab-nbgallery/autodownload/schemas/@jupyterlab-nbgallery/autodownload/autodownload.json
jupyterlab_nbgallery-3.0.6.data/data/share/jupyter/labextensions/@jupyterlab-nbgallery/autodownload/schemas/@jupyterlab-nbgallery/autodownload/package.json.orig
jupyterlab_nbgallery-3.0.6.data/data/share/jupyter/labextensions/@jupyterlab-nbgallery/autodownload/static/509.0ac8678728beba73cd83.js
jupyterlab_nbgallery-3.0.6.data/data/share/jupyter/labextensions/@jupyterlab-nbgallery/autodownload/static/603.fdb8e6deec8a3b7387be.js
jupyterlab_nbgallery-3.0.6.data/data/share/jupyter/labextensions/@jupyterlab-nbgallery/autodownload/static/616.a017de9fe25abae87bc7.js
jupyterlab_nbgallery-3.0.6.data/data/share/jupyter/labextensions/@jupyterlab-nbgallery/autodownload/static/616.a017de9fe25abae87bc7.js.LICENSE.txt
jupyterlab_nbgallery-3.0.6.data/data/share/jupyter/labextensions/@jupyterlab-nbgallery/autodownload/static/remoteEntry.b1002c3be0e6df9c7f0a.js
jupyterlab_nbgallery-3.0.6.data/data/share/jupyter/labextensions/@jupyterlab-nbgallery/autodownload/static/style.js
jupyterlab_nbgallery-3.0.6.data/data/share/jupyter/labextensions/@jupyterlab-nbgallery/autodownload/static/third-party-licenses.json
jupyterlab_nbgallery-3.0.6.data/data/share/jupyter/labextensions/@jupyterlab-nbgallery/environment-life/package.json
jupyterlab_nbgallery-3.0.6.data/data/share/jupyter/labextensions/@jupyterlab-nbgallery/environment-life/schemas/@jupyterlab-nbgallery/environment-life/package.json.orig
jupyterlab_nbgallery-3.0.6.dist-info/licenses/LICENSE
jupyterlab_nbgallery-3.0.6.dist-info/METADATA
jupyterlab_nbgallery-3.0.6.dist-info/WHEEL
jupyterlab_nbgallery-3.0.6.dist-info/top_level.txt
jupyterlab_nbgallery-3.0.6.dist-info/RECORD
