Metadata-Version: 2.4
Name: jupyterlab_nbgallery
Version: 3.0.6
Summary: A JupyterLab Extension for NBGallery integration
Home-page: https://github.com/nbgallery/lab-extensions
Author: NBGallery
License: MIT
Keywords: Jupyter,JupyterLab
Platform: Linux
Platform: Mac OS X
Platform: Windows
Classifier: License :: OSI Approved :: BSD License
Classifier: Programming Language :: Python
Classifier: Programming Language :: Python :: 3
Classifier: Programming Language :: Python :: 3.6
Classifier: Programming Language :: Python :: 3.7
Classifier: Programming Language :: Python :: 3.8
Classifier: Framework :: Jupyter
License-File: LICENSE
Requires-Dist: jupyterlab>=4.0.0
Requires-Dist: jupyter_server>=2
Dynamic: author
Dynamic: classifier
Dynamic: description
Dynamic: description-content-type
Dynamic: home-page
Dynamic: keywords
Dynamic: license
Dynamic: license-file
Dynamic: platform
Dynamic: requires-dist
Dynamic: summary
